README.rst
setup.py
hwd/__init__.py
hwd/network.py
hwd/storage.py
hwd/udev.py
hwd/wrapper.py
hwd.egg-info/PKG-INFO
hwd.egg-info/SOURCES.txt
hwd.egg-info/dependency_links.txt
hwd.egg-info/requires.txt
hwd.egg-info/top_level.txt