Metadata-Version: 1.1
Name: hwd
Version: 0.3
Summary: UNKNOWN
Home-page: https://github.com/Outernet-Project/hwd
Author: UNKNOWN
Author-email: UNKNOWN
License: GPLv3
Platform: UNKNOWN
Classifier: Development Status :: 2 - Pre-Alpha
Classifier: Intended Audience :: Developers
Classifier: Intended Audience :: System Administrators
Classifier: License :: OSI Approved :: GNU General Public License v3 or later (GPLv3+)
Classifier: Topic :: System :: Hardware
Classifier: Topic :: Utilities
